avasar/__init__.py
avasar/__main__.py
avasar/data/blades.toml
avasar/data/firstname-english-female.toml
avasar/data/firstname-english-male.toml
avasar/data/firstname-german-female.toml
avasar/data/firstname-german-male.toml
avasar/data/lastname-english.toml
avasar/data/lastname-german.toml
avasar/data/person.py
avasar/data/person.toml
avasar/data/places.toml
avasar/dsl.py
avasar/main.py
avasar-0.7.1.dist-info/METADATA
avasar-0.7.1.dist-info/WHEEL
avasar-0.7.1.dist-info/entry_points.txt
avasar-0.7.1.dist-info/RECORD
