Metadata-Version: 2.1
Name: avasar
Version: 0.7.1
Summary: Text generation DSL in python
License: AGPL-3.0-or-later
Author: Streampunk
Author-email: glad.car1474@fastmail.com
Requires-Python: >=3.10,<4.0
Classifier: License :: OSI Approved :: GNU Affero General Public License v3 or later (AGPLv3+)
Classifier: Programming Language :: Python :: 3
Classifier: Programming Language :: Python :: 3.10
Classifier: Programming Language :: Python :: 3.11
Requires-Dist: toml (>=0.10.2,<0.11.0)
